<?xml version="1.0" encoding="utf-8" ?>
<dwsync>
<file name="image_01_l.jpg" server="192.168.1.140//new/" local="129557303880000000" remote="130040494200000000" />
<file name="image_01_s.jpg" server="192.168.1.140//new/" local="129557303920000000" remote="130040494200000000" />
<file name="image_02_l.jpg" server="192.168.1.140//new/" local="129557304000000000" remote="130040494200000000" />
<file name="image_02_s.jpg" server="192.168.1.140//new/" local="129557304040000000" remote="130040494200000000" />
<file name="image_03_l.jpg" server="192.168.1.140//new/" local="129557304120000000" remote="130040494200000000" />
<file name="image_03_s.jpg" server="192.168.1.140//new/" local="129557304160000000" remote="130040494200000000" />
<file name="image_04_l.jpg" server="192.168.1.140//new/" local="129557304240000000" remote="130040494200000000" />
<file name="image_04_s.jpg" server="192.168.1.140//new/" local="129557304280000000" remote="130040494200000000" />
</dwsync>